{
  "header": {
    "content_type": "master_text"
  },
  "payload": [
    {
      "id": "10",
      "ja_JP": "採取時間短縮",
      "zh_TW": "採集時間縮短"
    },
    {
      "id": "12",
      "ja_JP": "エネミーからのドロップ率増加",
      "zh_TW": "敵人素材掉落率增加"
    },
    {
      "id": "15",
      "ja_JP": "商業施設の費用割引",
      "zh_TW": "商店費用折扣"
    },
    {
      "id": "17",
      "ja_JP": "ミッション報酬のGC増加",
      "zh_TW": "副本獎勵GC增加"
    },
    {
      "id": "18",
      "ja_JP": "チーム経験値増加",
      "zh_TW": "團隊經驗值增加"
    },
    {
      "id": "19",
      "ja_JP": "アイテム売却額増加",
      "zh_TW": "道具販賣額增加"
    },
    {
      "id": "20",
      "ja_JP": "採取個数増加",
      "zh_TW": "採集個數增加"
    },
    {
      "id": "259",
      "ja_JP": "武器クラフトルーノ割引",
      "zh_TW": "武器製作魯諾折扣"
    },
    {
      "id": "272",
      "ja_JP": "エネミー経験値増加",
      "zh_TW": "敵人經驗值增加"
    },
    {
      "id": "48",
      "ja_JP": "(実機非表示)採取時間短縮 -{value}秒",
      "zh_TW": "(實機不會顯示)採集時間縮短 -{value}秒"
    },
    {
      "id": "49",
      "ja_JP": "(実機非表示)採取時間短縮 -{value}秒",
      "zh_TW": "(實機不會顯示)採集時間縮短 -{value}秒"
    },
    {
      "id": "50",
      "ja_JP": "(実機非表示)採取時間短縮 -{value}秒",
      "zh_TW": "(實機不會顯示)採集時間縮短 -{value}秒"
    },
    {
      "id": "54",
      "ja_JP": "(実機非表示)エネミー ドロップ率上昇 +{value}% (回数制限) {count}回",
      "zh_TW": "(實機不會顯示)敵人 掉落率上升 +{value}% (次數限制) {count}次"
    },
    {
      "id": "55",
      "ja_JP": "(実機非表示)エネミー ドロップ率上昇 +{value}% (回数制限) {count}回",
      "zh_TW": "(實機不會顯示)敵人 掉落率上升 +{value}% (次數限制) {count}次"
    },
    {
      "id": "56",
      "ja_JP": "(実機非表示)エネミー ドロップ率上昇 +{value}% (回数制限) {count}回",
      "zh_TW": "(實機不會顯示)敵人 掉落率上升 +{value}% (次數限制) {count}次"
    },
    {
      "id": "63",
      "ja_JP": "(実機非表示)NPC施設 ルーノ消費量の減少 -{value}% (回数制限) {count}回",
      "zh_TW": "(實機不會顯示)NPC設施 魯諾消耗量減少 -{value}% (次數限制) {count}次"
    },
    {
      "id": "64",
      "ja_JP": "(実機非表示)NPC施設 ルーノ消費量の減少 -{value}% (回数制限) {count}回",
      "zh_TW": "(實機不會顯示)NPC設施 魯諾消耗量減少 -{value}% (次數限制) {count}次"
    },
    {
      "id": "65",
      "ja_JP": "(実機非表示)NPC施設 ルーノ消費量の減少 -{value}% (回数制限) {count}回",
      "zh_TW": "(實機不會顯示)NPC設施 魯諾消耗量減少 -{value}% (次數限制) {count}次"
    },
    {
      "id": "66",
      "ja_JP": "(実機非表示)クラフト(武器) 大成功率アップ  (回数制限) {count}回",
      "zh_TW": "(實機不會顯示)製作(武器) 大成功率UP  (次數限制) {count}次"
    },
    {
      "id": "67",
      "ja_JP": "(実機非表示)クラフト(武器) 大成功率アップ  (回数制限) {count}回",
      "zh_TW": "(實機不會顯示)製作(武器) 大成功率UP  (次數限制) {count}次"
    },
    {
      "id": "68",
      "ja_JP": "(実機非表示)クラフト(武器) 大成功率アップ  (回数制限) {count}回",
      "zh_TW": "(實機不會顯示)製作(武器) 大成功率UP  (次數限制) {count}次"
    },
    {
      "id": "69",
      "ja_JP": "(実機非表示)クラフト(バトルイマジン) 大成功率アップ  (回数制限) {count}回",
      "zh_TW": "(實機不會顯示)製作(戰鬥印象體) 大成功率UP  (次數限制) {count}次"
    },
    {
      "id": "70",
      "ja_JP": "(実機非表示)クラフト(バトルイマジン) 大成功率アップ  (回数制限) {count}回",
      "zh_TW": "(實機不會顯示)製作(戰鬥印象體) 大成功率UP  (次數限制) {count}次"
    },
    {
      "id": "71",
      "ja_JP": "(実機非表示)クラフト(バトルイマジン) 大成功率アップ  (回数制限) {count}回",
      "zh_TW": "(實機不會顯示)製作(戰鬥印象體) 大成功率UP  (次數限制) {count}次"
    },
    {
      "id": "72",
      "ja_JP": "(実機非表示)クラフト(インナーイマジン) 大成功率アップ  (回数制限) {count}回",
      "zh_TW": "(實機不會顯示)製作(強化印象體) 大成功率UP  (次數限制) {count}次"
    },
    {
      "id": "73",
      "ja_JP": "(実機非表示)クラフト(インナーイマジン) 大成功率アップ  (回数制限) {count}回",
      "zh_TW": "(實機不會顯示)製作(強化印象體) 大成功率UP  (次數限制) {count}次"
    },
    {
      "id": "74",
      "ja_JP": "(実機非表示)クラフト(インナーイマジン) 大成功率アップ  (回数制限) {count}回",
      "zh_TW": "(實機不會顯示)製作(強化印象體) 大成功率UP  (次數限制) {count}次"
    },
    {
      "id": "78",
      "ja_JP": "(実機非表示)ミッション達成時のGC獲得量アップ +{value}% (回数制限) {count}回",
      "zh_TW": "(實機不會顯示)任務達成時GC獲得量UP +{value}% (次數限制) {count}次"
    },
    {
      "id": "79",
      "ja_JP": "(実機非表示)ミッション達成時のGC獲得量アップ +{value}% (回数制限) {count}回",
      "zh_TW": "(實機不會顯示)任務達成時GC獲得量UP +{value}% (次數限制) {count}次"
    },
    {
      "id": "80",
      "ja_JP": "(実機非表示)ミッション達成時のGC獲得量アップ +{value}% (回数制限) {count}回",
      "zh_TW": "(實機不會顯示)任務達成時GC獲得量UP +{value}% (次數限制) {count}次"
    },
    {
      "id": "81",
      "ja_JP": "(実機非表示)チーム経験値獲得量アップ +{value}% (回数制限) {count}回",
      "zh_TW": "(實機不會顯示)團隊經驗值獲得量UP +{value}% (次數限制) {count}次"
    },
    {
      "id": "82",
      "ja_JP": "(実機非表示)チーム経験値獲得量アップ +{value}% (回数制限) {count}回",
      "zh_TW": "(實機不會顯示)團隊經驗值獲得量UP +{value}% (次數限制) {count}次"
    },
    {
      "id": "83",
      "ja_JP": "(実機非表示)チーム経験値獲得量アップ +{value}% (回数制限) {count}回",
      "zh_TW": "(實機不會顯示)團隊經驗值獲得量UP +{value}% (次數限制) {count}次"
    },
    {
      "id": "84",
      "ja_JP": "(実機非表示)売却額アップ +{value}% (回数制限) {count}回",
      "zh_TW": "(實機不會顯示)販賣金額UP +{value}% (次數限制) {count}次"
    },
    {
      "id": "85",
      "ja_JP": "(実機非表示)売却額アップ +{value}% (回数制限) {count}回",
      "zh_TW": "(實機不會顯示)販賣金額UP +{value}% (次數限制) {count}次"
    },
    {
      "id": "86",
      "ja_JP": "(実機非表示)売却額アップ +{value}% (回数制限) {count}回",
      "zh_TW": "(實機不會顯示)販賣金額UP +{value}% (次數限制) {count}次"
    },
    {
      "id": "87",
      "ja_JP": "(実機非表示)マウントイマジンエネルギー消費量減少 -{value}%  {count}秒",
      "zh_TW": "(實機不會顯示)騎獸能量消耗量減少 -{value}%  {count}秒"
    },
    {
      "id": "88",
      "ja_JP": "(実機非表示)マウントイマジンエネルギー消費量減少 -{value}%  {count}秒",
      "zh_TW": "(實機不會顯示)騎獸能量消耗量減少 -{value}%  {count}秒"
    },
    {
      "id": "89",
      "ja_JP": "(実機非表示)マウントイマジンエネルギー消費量減少 -{value}%  {count}秒",
      "zh_TW": "(實機不會顯示)騎獸能量消耗量減少 -{value}%  {count}秒"
    },
    {
      "id": "90",
      "ja_JP": "(実機非表示)トレジャーレアリティーアップ +{value}%(回数制限) {count}回",
      "zh_TW": "(實機不會顯示)寶物稀有度UP +{value}%(次數限制) {count}次"
    },
    {
      "id": "91",
      "ja_JP": "(実機非表示)トレジャーレアリティーアップ +{value}%(回数制限) {count}回",
      "zh_TW": "(實機不會顯示)寶物稀有度UP +{value}%(次數限制) {count}次"
    },
    {
      "id": "92",
      "ja_JP": "(実機非表示)トレジャーレアリティーアップ +{value}%(回数制限) {count}回",
      "zh_TW": "(實機不會顯示)寶物稀有度UP +{value}%(次數限制) {count}次"
    },
    {
      "id": "93",
      "ja_JP": "(実機非表示)ドロップアイテム獲得数アップ +{value}% (回数制限) {count}回",
      "zh_TW": "(實機不會顯示)掉落道具獲得數UP +{value}% (次數限制) {count}次"
    },
    {
      "id": "94",
      "ja_JP": "(実機非表示)ドロップアイテム獲得数アップ +{value}% (回数制限) {count}回",
      "zh_TW": "(實機不會顯示)掉落道具獲得數UP +{value}% (次數限制) {count}次"
    },
    {
      "id": "95",
      "ja_JP": "(実機非表示)ドロップアイテム獲得数アップ +{value}% (回数制限) {count}回",
      "zh_TW": "(實機不會顯示)掉落道具獲得數UP +{value}% (次數限制) {count}次"
    },
    {
      "id": "96",
      "ja_JP": "(実機非表示)融着精度アップ +{value}% (回数制限) {count}回",
      "zh_TW": "(實機不會顯示)融合精確度UP +{value}% (次數限制) {count}次"
    },
    {
      "id": "97",
      "ja_JP": "(実機非表示)融着精度アップ +{value}% (回数制限) {count}回",
      "zh_TW": "(實機不會顯示)融合精確度UP +{value}% (次數限制) {count}次"
    },
    {
      "id": "98",
      "ja_JP": "(実機非表示)融着精度アップ +{value}% (回数制限) {count}回",
      "zh_TW": "(實機不會顯示)融合精確度UP +{value}% (次數限制) {count}次"
    },
    {
      "id": "99",
      "ja_JP": "(実機非表示)採取獲得数アップ+{value}個(回数制限) {count}回",
      "zh_TW": "(實機不會顯示)採集獲得數UP +{value}個% (次數限制) {count}次"
    },
    {
      "id": "100",
      "ja_JP": "(実機非表示)採取獲得数アップ+{value}個(回数制限) {count}回",
      "zh_TW": "(實機不會顯示)採集獲得數UP +{value}個% (次數限制) {count}次"
    },
    {
      "id": "101",
      "ja_JP": "(実機非表示)採取獲得数アップ+{value}個(回数制限) {count}回",
      "zh_TW": "(實機不會顯示)採集獲得數UP +{value}個% (次數限制) {count}次"
    },
    {
      "id": "260",
      "ja_JP": "(実機非表示)武器クラフト ルーノ消費量の減少 -{value}% (回数制限) {count}回",
      "zh_TW": "(實機不會顯示)武器製作魯諾消耗量減少 -{value}% (次數限制) {count}次"
    },
    {
      "id": "261",
      "ja_JP": "(実機非表示)武器クラフト ルーノ消費量の減少 -{value}% (回数制限) {count}回",
      "zh_TW": "(實機不會顯示)武器製作魯諾消耗量減少 -{value}% (次數限制) {count}次"
    },
    {
      "id": "262",
      "ja_JP": "(実機非表示)武器クラフト ルーノ消費量の減少 -{value}% (回数制限) {count}回",
      "zh_TW": "(實機不會顯示)武器製作魯諾消耗量減少 -{value}% (次數限制) {count}次"
    },
    {
      "id": "273",
      "ja_JP": "(実機非表示)30レベルまでエネミー 獲得経験値上昇 +{value}% (回数制限) {count}回",
      "zh_TW": "(實機不會顯示)30級為止獲得敵人經驗值上升 +{value}% (次數) {count}次"
    },
    {
      "id": "274",
      "ja_JP": "(実機非表示)30レベルまでエネミー 獲得経験値上昇 +{value}% (回数制限) {count}回",
      "zh_TW": "(實機不會顯示)30級為止獲得敵人經驗值上升 +{value}% (次數) {count}次"
    },
    {
      "id": "275",
      "ja_JP": "(実機非表示)30レベルまでエネミー 獲得経験値上昇 +{value}% (回数制限) {count}回",
      "zh_TW": "(實機不會顯示)30級為止獲得敵人經驗值上升 +{value}% (次數) {count}次"
    },
    {
      "id": "129",
      "ja_JP": "採取時間が短縮する (Lv.1用)",
      "zh_TW": "採集時間縮短 (Lv.1用)"
    },
    {
      "id": "130",
      "ja_JP": "採取時間が短縮する (Lv.2用)",
      "zh_TW": "採集時間縮短 (Lv.2用)"
    },
    {
      "id": "131",
      "ja_JP": "採取時間が短縮する (Lv.3用)",
      "zh_TW": "採集時間縮短 (Lv.3用)"
    },
    {
      "id": "135",
      "ja_JP": "エネミーのドロップ率が上昇する (Lv.1用)",
      "zh_TW": "敵人掉落率上升(Lv.1用)"
    },
    {
      "id": "136",
      "ja_JP": "エネミーのドロップ率が上昇する (Lv.2用)",
      "zh_TW": "敵人掉落率上升(Lv.2用)"
    },
    {
      "id": "137",
      "ja_JP": "エネミーのドロップ率が上昇する (Lv.3用)",
      "zh_TW": "敵人掉落率上升(Lv.3用)"
    },
    {
      "id": "144",
      "ja_JP": "NPC施設でのルーノ消費量が減少する (Lv.1用)",
      "zh_TW": "NPC設施魯諾消耗量減少 (Lv.1用)"
    },
    {
      "id": "145",
      "ja_JP": "NPC施設でのルーノ消費量が減少する (Lv.2用)",
      "zh_TW": "NPC設施魯諾消耗量減少 (Lv.2用)"
    },
    {
      "id": "146",
      "ja_JP": "NPC施設でのルーノ消費量が減少する (Lv.3用)",
      "zh_TW": "NPC設施魯諾消耗量減少 (Lv.3用)"
    },
    {
      "id": "147",
      "ja_JP": "大成功率が上昇する (Lv.1用)",
      "zh_TW": "大成功率上升 (Lv.1用)"
    },
    {
      "id": "148",
      "ja_JP": "大成功率が上昇する (Lv.2用)",
      "zh_TW": "大成功率上升 (Lv.2用)"
    },
    {
      "id": "149",
      "ja_JP": "大成功率が上昇する (Lv.3用)",
      "zh_TW": "大成功率上升 (Lv.3用)"
    },
    {
      "id": "150",
      "ja_JP": "大成功率が上昇する (Lv.1用)",
      "zh_TW": "大成功率上升 (Lv.1用)"
    },
    {
      "id": "151",
      "ja_JP": "大成功率が上昇する (Lv.2用)",
      "zh_TW": "大成功率上升 (Lv.2用)"
    },
    {
      "id": "152",
      "ja_JP": "大成功率が上昇する (Lv.3用)",
      "zh_TW": "大成功率上升 (Lv.3用)"
    },
    {
      "id": "153",
      "ja_JP": "大成功率が上昇する (Lv.1用)",
      "zh_TW": "大成功率上升 (Lv.1用)"
    },
    {
      "id": "154",
      "ja_JP": "大成功率が上昇する (Lv.2用)",
      "zh_TW": "大成功率上升 (Lv.2用)"
    },
    {
      "id": "155",
      "ja_JP": "大成功率が上昇する (Lv.3用)",
      "zh_TW": "大成功率上升 (Lv.3用)"
    },
    {
      "id": "159",
      "ja_JP": "GC獲得量が上昇する (Lv.1用)",
      "zh_TW": "GC獲得量上升 (Lv.1用)"
    },
    {
      "id": "160",
      "ja_JP": "GC獲得量が上昇する (Lv.2用)",
      "zh_TW": "GC獲得量上升 (Lv.2用)"
    },
    {
      "id": "161",
      "ja_JP": "GC獲得量が上昇する (Lv.3用)",
      "zh_TW": "GC獲得量上升 (Lv.3用)"
    },
    {
      "id": "162",
      "ja_JP": "チーム経験値獲得量が上昇する (Lv.1用)",
      "zh_TW": "團隊經驗值獲得量上升 (Lv.1用)"
    },
    {
      "id": "163",
      "ja_JP": "チーム経験値獲得量が上昇する (Lv.2用)",
      "zh_TW": "團隊經驗值獲得量上升 (Lv.2用)"
    },
    {
      "id": "164",
      "ja_JP": "チーム経験値獲得量が上昇する (Lv.3用)",
      "zh_TW": "團隊經驗值獲得量上升 (Lv.3用)"
    },
    {
      "id": "165",
      "ja_JP": "売却額が上昇する (Lv.1用)",
      "zh_TW": "販賣金額上升 (Lv.1用)"
    },
    {
      "id": "166",
      "ja_JP": "売却額が上昇する (Lv.2用)",
      "zh_TW": "販賣金額上升 (Lv.2用)"
    },
    {
      "id": "167",
      "ja_JP": "売却額が上昇する (Lv.3用)",
      "zh_TW": "販賣金額上升 (Lv.3用)"
    },
    {
      "id": "168",
      "ja_JP": "マウントイマジン消費量が減少する (Lv.1用)",
      "zh_TW": "騎獸能量消耗量減少(Lv.1用)"
    },
    {
      "id": "169",
      "ja_JP": "マウントイマジン消費量が減少する (Lv.2用)",
      "zh_TW": "騎獸能量消耗量減少(Lv.2用)"
    },
    {
      "id": "170",
      "ja_JP": "マウントイマジン消費量が減少する (Lv.3用)",
      "zh_TW": "騎獸能量消耗量減少(Lv.3用)"
    },
    {
      "id": "171",
      "ja_JP": "トレジャーレアリティーが上昇する(Lv.1用)",
      "zh_TW": "寶物稀有度上升 (Lv.1用)"
    },
    {
      "id": "172",
      "ja_JP": "トレジャーレアリティーが上昇する(Lv.2用)",
      "zh_TW": "寶物稀有度上升 (Lv.2用)"
    },
    {
      "id": "173",
      "ja_JP": "トレジャーレアリティーが上昇する(Lv.3用)",
      "zh_TW": "寶物稀有度上升 (Lv.3用)"
    },
    {
      "id": "174",
      "ja_JP": "ドロップアイテム獲得数が上昇する (Lv.1用)",
      "zh_TW": "掉落道具獲得數上升 (Lv.1用)"
    },
    {
      "id": "175",
      "ja_JP": "ドロップアイテム獲得数が上昇する (Lv.2用)",
      "zh_TW": "掉落道具獲得數上升 (Lv.2用)"
    },
    {
      "id": "176",
      "ja_JP": "ドロップアイテム獲得数が上昇する (Lv.3用)",
      "zh_TW": "掉落道具獲得數上升 (Lv.3用)"
    },
    {
      "id": "177",
      "ja_JP": "融着精度が上昇する (Lv.1用)",
      "zh_TW": "融合精確度上升 (Lv.1用)"
    },
    {
      "id": "178",
      "ja_JP": "融着精度が上昇する (Lv.2用)",
      "zh_TW": "融合精確度上升 (Lv.2用)"
    },
    {
      "id": "179",
      "ja_JP": "融着精度が上昇する (Lv.3用)",
      "zh_TW": "融合精確度上升 (Lv.3用)"
    },
    {
      "id": "180",
      "ja_JP": "採取獲得数が上昇する (Lv.1用)",
      "zh_TW": "採集獲得數上升 (Lv.1用)"
    },
    {
      "id": "181",
      "ja_JP": "採取獲得数が上昇する (Lv.2用)",
      "zh_TW": "採集獲得數上升 (Lv.2用)"
    },
    {
      "id": "182",
      "ja_JP": "採取獲得数が上昇する (Lv.3用)",
      "zh_TW": "採集獲得數上升 (Lv.3用)"
    },
    {
      "id": "263",
      "ja_JP": "武器クラフトのルーノ消費量が減少する (Lv.1用)",
      "zh_TW": "武器製作魯諾消耗量減少 (Lv.1用)"
    },
    {
      "id": "264",
      "ja_JP": "武器クラフトのルーノ消費量が減少する (Lv.2用)",
      "zh_TW": "武器製作魯諾消耗量減少 (Lv.2用)"
    },
    {
      "id": "265",
      "ja_JP": "武器クラフトのルーノ消費量が減少する (Lv.3用)",
      "zh_TW": "武器製作魯諾消耗量減少 (Lv.3用)"
    },
    {
      "id": "276",
      "ja_JP": "エネミー撃破の獲得経験値率が上昇する (Lv.1用)",
      "zh_TW": "敵人討伐獲得經驗值上升 (Lv.1用)"
    },
    {
      "id": "277",
      "ja_JP": "エネミー撃破の獲得経験値率が上昇する (Lv.2用)",
      "zh_TW": "敵人討伐獲得經驗值上升 (Lv.2用)"
    },
    {
      "id": "278",
      "ja_JP": "エネミー撃破の獲得経験値率が上昇する (Lv.3用)",
      "zh_TW": "敵人討伐獲得經驗值上升 (Lv.3用)"
    },
    {
      "id": "183",
      "ja_JP": "時間経過",
      "zh_TW": "時間經過"
    },
    {
      "id": "184",
      "ja_JP": "エネミーを撃破する",
      "zh_TW": "討伐敵人"
    },
    {
      "id": "185",
      "ja_JP": "採取する",
      "zh_TW": "採集"
    },
    {
      "id": "186",
      "ja_JP": "バトルイマジンをクラフトする",
      "zh_TW": "製作戰鬥印象體"
    },
    {
      "id": "187",
      "ja_JP": "バトルイマジンを精練する",
      "zh_TW": "精煉戰鬥印象體"
    },
    {
      "id": "188",
      "ja_JP": "宝箱を開ける",
      "zh_TW": "開啟寶箱"
    },
    {
      "id": "189",
      "ja_JP": "クラフトをする",
      "zh_TW": "製作時魯諾折扣"
    },
    {
      "id": "190",
      "ja_JP": "武器精練で装備のレベルアップ",
      "zh_TW": "透過武器精煉讓裝備升級"
    },
    {
      "id": "191",
      "ja_JP": "インナーイマジンレベルアップ",
      "zh_TW": "強化印象體升級"
    },
    {
      "id": "192",
      "ja_JP": "バトルイマジンレベルアップ",
      "zh_TW": "戰鬥印象體升級"
    },
    {
      "id": "193",
      "ja_JP": "武器融着を行う",
      "zh_TW": "執行武器融合"
    },
    {
      "id": "194",
      "ja_JP": "リキッドメモリを飲む",
      "zh_TW": "飲用液態記憶體"
    },
    {
      "id": "195",
      "ja_JP": "レイドミッションに参加する",
      "zh_TW": "參加Raid Boss戰"
    },
    {
      "id": "196",
      "ja_JP": "タイムアタックに参加する",
      "zh_TW": "參加計時賽"
    },
    {
      "id": "197",
      "ja_JP": "ラッシュバトルに参加する",
      "zh_TW": "參加競技場"
    },
    {
      "id": "198",
      "ja_JP": "「放浪の美食屋の料理を食べる/ハッピーナッポに話しかける/エングラム泉を使用」\nのいずれかを行う",
      "zh_TW": "執行「食用流浪美食家料理/與快樂納波說話/使用記憶痕跡泉」其中之一"
    },
    {
      "id": "199",
      "ja_JP": "「map.xlsxのenum_game_mode」を〇回クリアする'",
      "zh_TW": "「map.xlsxのenum_game_mode」完成〇次'"
    },
    {
      "id": "200",
      "ja_JP": "ルーノを獲得する",
      "zh_TW": "獲得魯諾"
    },
    {
      "id": "201",
      "ja_JP": "ルーノを消費する",
      "zh_TW": "消耗魯諾"
    },
    {
      "id": "202",
      "ja_JP": "ネームドエネミーを撃破する",
      "zh_TW": "討伐冠名級敵人"
    },
    {
      "id": "203",
      "ja_JP": "トークンを入手する",
      "zh_TW": "獲得代幣"
    },
    {
      "id": "204",
      "ja_JP": "スキルを使用する",
      "zh_TW": "使用技能"
    },
    {
      "id": "205",
      "ja_JP": "追跡調査隊を利用する",
      "zh_TW": "利用追跡調查隊"
    },
    {
      "id": "206",
      "ja_JP": "GCを獲得する",
      "zh_TW": "獲得GC"
    },
    {
      "id": "207",
      "ja_JP": "アイテムを入手する",
      "zh_TW": "獲得道具"
    },
    {
      "id": "208",
      "ja_JP": "アイテムを使用する",
      "zh_TW": "使用道具"
    },
    {
      "id": "209",
      "ja_JP": "蘇生を成功させる",
      "zh_TW": "成功復活"
    },
    {
      "id": "210",
      "ja_JP": "連綿の塔に参加する",
      "zh_TW": "參加高塔生存戰"
    },
    {
      "id": "211",
      "ja_JP": "スコアアタックに参加する",
      "zh_TW": "參加積分戰"
    },
    {
      "id": "242",
      "ja_JP": "エネミーを撃破する",
      "zh_TW": "討伐敵人"
    },
    {
      "id": "243",
      "ja_JP": "ミッションをクリアする",
      "zh_TW": "通關副本"
    },
    {
      "id": "244",
      "ja_JP": "ラッシュバトルに参加する",
      "zh_TW": "參加競技場"
    },
    {
      "id": "246",
      "ja_JP": "リキッドメモリを飲む",
      "zh_TW": "飲用液態記憶體"
    },
    {
      "id": "255",
      "ja_JP": "シナリオミッションをクリアする",
      "zh_TW": "通關主線副本"
    },
    {
      "id": "266",
      "ja_JP": "ミッションをクリアする",
      "zh_TW": "通關副本"
    },
    {
      "id": "267",
      "ja_JP": "エネミーを撃破する",
      "zh_TW": "討伐敵人"
    },
    {
      "id": "270",
      "ja_JP": "シナリオミッションをクリアする",
      "zh_TW": "通關主線副本"
    },
    {
      "id": "212",
      "ja_JP": "{value}分経過でM1等級分貯まる。ログイン状況は問わない。\nM1等級分以上は貯まらない",
      "zh_TW": "每經過{value}分將會儲存M1等級分量。無論登入狀況為何。\nM1等級分量以上的量將不會儲存"
    },
    {
      "id": "213",
      "ja_JP": "エネミーを1匹倒す毎に一定量が貯まる",
      "zh_TW": "每次擊敗怪物都會累積一定數量"
    },
    {
      "id": "214",
      "ja_JP": "採取を1回行う毎に一定量が貯まる",
      "zh_TW": "每次採集都會積累一定數量"
    },
    {
      "id": "215",
      "ja_JP": "バトルイマジンを{value}回クラフトする毎にランダム量が貯まる",
      "zh_TW": "每將戰鬥印象體進行{value}次製作時會累積隨機數量"
    },
    {
      "id": "216",
      "ja_JP": "バトルイマジンを{value}回精練する毎にランダム量が貯まる",
      "zh_TW": "每將戰鬥印象體進行{value}次精煉時會累積隨機數量"
    },
    {
      "id": "217",
      "ja_JP": "宝箱を{value}回開ける毎にランダム量が貯まる",
      "zh_TW": "每開啟寶箱{value}次時會累積隨機數量"
    },
    {
      "id": "218",
      "ja_JP": "クラフトを{value}回実行する毎にランダム量が貯まる",
      "zh_TW": "每製作{value}次時會累積隨機數量"
    },
    {
      "id": "219",
      "ja_JP": "武器を{value}レベル上げる毎にランダム量が貯まる",
      "zh_TW": "每提升武器{value}級時會累積隨機數量"
    },
    {
      "id": "220",
      "ja_JP": "インナーマジンを{value}レベル上げる毎にランダム量が貯まる",
      "zh_TW": "每將強化印象體提升{value}級時會累積隨機數量"
    },
    {
      "id": "221",
      "ja_JP": "バトルイマジンを{value}レベル上げる毎にランダム量が貯まる",
      "zh_TW": "每將戰鬥印象體提升{value}級時會累積隨機數量"
    },
    {
      "id": "222",
      "ja_JP": "武器融着を{value}回実行する毎にランダム量が貯まる",
      "zh_TW": "每執行武器融合{value}次時會累積隨機數量"
    },
    {
      "id": "223",
      "ja_JP": "リキッドメモリを{value}回飲む毎にランダム量が貯まる",
      "zh_TW": "每飲用液態記憶體{value}次時會累積隨機數量"
    },
    {
      "id": "224",
      "ja_JP": "レイドミッションに{value}回参加毎にランダム量が貯まる",
      "zh_TW": "每參加Raid Boss戰{value}次時會累積隨機數量"
    },
    {
      "id": "225",
      "ja_JP": "タイムアタックに{value}回参加する毎にランダム量が貯まる",
      "zh_TW": "每參加積分戰{value}次時會累積隨機數量"
    },
    {
      "id": "226",
      "ja_JP": "ラッシュバトルに{value}回参加する毎にランダム量が貯まる",
      "zh_TW": "每參加競技場{value}次時會累積隨機數量"
    },
    {
      "id": "227",
      "ja_JP": "「放浪の美食屋の料理を食べる/ハッピーナッポに話しかける/エングラム泉を使用」\nのいずれかを{value}回行う毎にランダム量が貯まる",
      "zh_TW": "每執行「食用流浪美食家料理/與快樂納波說話/使用記憶痕跡泉」其中之一{value}次時會累積隨機數量"
    },
    {
      "id": "228",
      "ja_JP": "マップモードを{value}回クリアする毎にランダム量が貯まる",
      "zh_TW": "每使用地圖模式{value}次會累積隨機數量"
    },
    {
      "id": "229",
      "ja_JP": "ルーノを{value}獲得する毎にランダム量が貯まる",
      "zh_TW": "每獲得魯諾{value}時會累積隨機數量"
    },
    {
      "id": "230",
      "ja_JP": "ルーノを{value}消費する毎にランダム量が貯まる",
      "zh_TW": "每獲消耗諾{value}時會累積隨機數量"
    },
    {
      "id": "231",
      "ja_JP": "ネームドエネミーを{value}回撃破する毎にランダム量が貯まる",
      "zh_TW": "每討伐冠名級敵人{value}次時會累積隨機數量"
    },
    {
      "id": "232",
      "ja_JP": "トークンを{value}回入手する毎にランダム量が貯まる",
      "zh_TW": "每使用代幣{value}次時會累積隨機數量"
    },
    {
      "id": "233",
      "ja_JP": "スキルを{value}回使用する毎にランダム量が貯まる",
      "zh_TW": "每使用技能{value}次時會累積隨機數量"
    },
    {
      "id": "234",
      "ja_JP": "追跡調査隊を{value}回利用する毎にランダム量が貯まる",
      "zh_TW": "每使用追跡調查隊{value}次時會累積隨機數量"
    },
    {
      "id": "235",
      "ja_JP": "GCを{value}獲得する毎にランダム量が貯まる",
      "zh_TW": "每獲得GC{value}時會累積隨機數量"
    },
    {
      "id": "236",
      "ja_JP": "アイテムを{value}回入手する毎にランダム量が貯まる",
      "zh_TW": "每獲得道具{value}次時會累積隨機數量"
    },
    {
      "id": "237",
      "ja_JP": "アイテムを{value}回使用する毎にランダム量が貯まる",
      "zh_TW": "每使用道具{value}次時會累積隨機數量"
    },
    {
      "id": "238",
      "ja_JP": "蘇生を{value}回成功させる毎にランダム量が貯まる",
      "zh_TW": "每成功復活{value}次時會累積隨機數量"
    },
    {
      "id": "239",
      "ja_JP": "連綿の塔に{value}回参加する毎にランダム量が貯まる",
      "zh_TW": "每參加高塔生存戰{value}次時會累積隨機數量"
    },
    {
      "id": "240",
      "ja_JP": "スコアアタックに{value}回参加する毎にランダム量が貯まる",
      "zh_TW": "每參加積分戰{value}次時會累積隨機數量"
    },
    {
      "id": "249",
      "ja_JP": "エネミーを{value}匹倒す毎に一定量が貯まる",
      "zh_TW": "每打倒敵人{value}隻時會累積一定數量"
    },
    {
      "id": "250",
      "ja_JP": "ミッションを1回クリアする毎に一定量が貯まる",
      "zh_TW": "每通關副本{value}次時會累積一定數量"
    },
    {
      "id": "251",
      "ja_JP": "ラッシュバトルに1回参加する毎に一定量が貯まる",
      "zh_TW": "每參加1次競技場時會累積一定數量"
    },
    {
      "id": "253",
      "ja_JP": "リキッドメモリを1回飲む毎に一定量が貯まる",
      "zh_TW": "每飲用液態記憶體會累積一定數量"
    },
    {
      "id": "256",
      "ja_JP": "シナリオミッションを1回クリアする毎に一定量が貯まる",
      "zh_TW": "每通關1次主線副本時會累積一定數量"
    },
    {
      "id": "268",
      "ja_JP": "ミッションを1回クリアする毎に一定量が貯まる",
      "zh_TW": "每通關1次副本時會累積一定數量"
    },
    {
      "id": "269",
      "ja_JP": "エネミーを1匹倒す毎に一定量が貯まる",
      "zh_TW": "每打倒1隻敵人時會累積一定數量"
    },
    {
      "id": "271",
      "ja_JP": "シナリオミッションを1回クリアする毎に一定量が貯まる",
      "zh_TW": "每通關1次主線副本時會累積一定數量"
    }
  ]
}