{
  "header": {
    "content_type": "master_text"
  },
  "payload": [
    {
      "id": "98",
      "ja_JP": "失われた壁画のピース",
      "zh_TW": "散失的壁畫碎片"
    },
    {
      "id": "99",
      "ja_JP": "飲み込まれた壁画のピース",
      "zh_TW": "被吞噬的壁畫碎片"
    },
    {
      "id": "100",
      "ja_JP": "奪い取られた壁画のピース",
      "zh_TW": "被奪走的壁畫碎片"
    },
    {
      "id": "1",
      "ja_JP": "お祭りとフェイクスイーツ",
      "zh_TW": "祭典與甜點模型"
    },
    {
      "id": "2",
      "ja_JP": "大食らいとフェイクスイーツ",
      "zh_TW": "大胃王與甜點模型"
    },
    {
      "id": "3",
      "ja_JP": "イタズラとフェイクスイーツ",
      "zh_TW": "惡作劇與甜點模型"
    },
    {
      "id": "4",
      "ja_JP": "水着で駆け出せ！　眩しい夏！",
      "zh_TW": "穿上泳裝衝吧！眩目的夏日！"
    },
    {
      "id": "5",
      "ja_JP": "夏の視線をひとり占め！",
      "zh_TW": "獨佔夏天的視線!"
    },
    {
      "id": "6",
      "ja_JP": "さらにさらに釘づけに！",
      "zh_TW": "更加更加地緊盯!"
    },
    {
      "id": "7",
      "ja_JP": "フワフワ綿毛集め",
      "zh_TW": "收集柔軟的棉毛"
    },
    {
      "id": "8",
      "ja_JP": "儚きフワフワスーツ",
      "zh_TW": "夢幻般的輕飄飄西裝"
    },
    {
      "id": "9",
      "ja_JP": "極上のフワフワを包み込んで",
      "zh_TW": "塞入極品的柔軟"
    },
    {
      "id": "10",
      "ja_JP": "彼方からロマンの波音",
      "zh_TW": "遠方傳來的浪漫波浪聲"
    },
    {
      "id": "11",
      "ja_JP": "天を映すロマンの欠片",
      "zh_TW": "映照天空的浪漫碎片"
    },
    {
      "id": "12",
      "ja_JP": "執念深きロマンの邪魔者",
      "zh_TW": "執念強的浪漫礙事者"
    },
    {
      "id": "135",
      "ja_JP": "花びらに想いを込めて",
      "zh_TW": "將回憶寫入花瓣中"
    },
    {
      "id": "136",
      "ja_JP": "花びらと狩人の伝説",
      "zh_TW": "花瓣與獵人的傳說"
    },
    {
      "id": "137",
      "ja_JP": "舞う花びらに危難の香り",
      "zh_TW": "舞動的花瓣散發著危險氣息"
    },
    {
      "id": "13",
      "ja_JP": "キングコレクター！　のコイン",
      "zh_TW": "王牌收藏家硬幣！"
    },
    {
      "id": "14",
      "ja_JP": "キラリとフラッシュ！　なコイン",
      "zh_TW": "閃閃耀耀!的金幣"
    },
    {
      "id": "15",
      "ja_JP": "ナイスファイト！　じゃないコイン",
      "zh_TW": "做得不錯！才怪的金幣"
    },
    {
      "id": "62",
      "ja_JP": "香りはまさに刺激的！",
      "zh_TW": "香氣簡直是太刺激!"
    },
    {
      "id": "63",
      "ja_JP": "刺激的にゴブリン撃退！",
      "zh_TW": "擊退刺激的哥布林!"
    },
    {
      "id": "64",
      "ja_JP": "刺激的に異文化交流！！",
      "zh_TW": "刺激的文化交流!!"
    },
    {
      "id": "110",
      "ja_JP": "空より降りたる願い星",
      "zh_TW": "從天空而降的許願星"
    },
    {
      "id": "111",
      "ja_JP": "両手いっぱいの願いごと",
      "zh_TW": "雙手滿滿的願望"
    },
    {
      "id": "112",
      "ja_JP": "願いの熱はほどほどに",
      "zh_TW": "適度的願望熱誠"
    },
    {
      "id": "74",
      "ja_JP": "聖夜に健やかな願いを",
      "zh_TW": "在聖夜中許下健康的願望"
    },
    {
      "id": "75",
      "ja_JP": "聖夜の夢は安らかに",
      "zh_TW": "安詳的聖夜之夢"
    },
    {
      "id": "76",
      "ja_JP": "最高の聖夜をプレゼント",
      "zh_TW": "最棒的聖夜禮物"
    },
    {
      "id": "86",
      "ja_JP": "新しい春を呼ぼう",
      "zh_TW": "呼唤春天吧"
    },
    {
      "id": "87",
      "ja_JP": "新しいライバル登場！",
      "zh_TW": "新的勁敵登場!"
    },
    {
      "id": "88",
      "ja_JP": "新しい君に祝福を",
      "zh_TW": "給新人祝福"
    },
    {
      "id": "122",
      "ja_JP": "甘～いお菓子は感謝の印",
      "zh_TW": "甜蜜的糖果是感恩的象徵"
    },
    {
      "id": "123",
      "ja_JP": "甘～くカラフルな遊び心",
      "zh_TW": "甜蜜多彩俏皮"
    },
    {
      "id": "124",
      "ja_JP": "甘～い気持ちをおすそ分け",
      "zh_TW": "分享甜蜜的心情"
    },
    {
      "id": "101",
      "ja_JP": "やあ！　冒険は順調かい？\nボクの名はヴァーレン。相棒はカルネラ。\n蒐集家『キングコレクター』様の使いをしている者さ！\nボクらは今、主人の命令で『古代壁画のピース』を集めている。\n君もよかったら、手を貸してくれないかな？\nボクらの依頼を受けて、より多くの『古代壁画のピース』を手に入れてくれ！　よろしく頼むよ、ハッハァー！",
      "zh_TW": "嘿！冒險還順利嗎？\n我叫做瓦倫。同伴是卡涅拉。\n我們是蒐藏家『王牌收藏家』大人的使者！\n我們現在奉主人之命，正在收集『古代壁畫的碎片』。\n如果你方便的話，可以來幫個忙嗎？\n接受我們的委託，並取得更多『古代壁畫的碎片』吧！　\n拜託啦！哈哈！"
    },
    {
      "id": "102",
      "ja_JP": "ハッハァー！　『キングコレクター』様の使い、ヴァーレンさ！\n『古代壁画のピース』は集まっているかい？\n実は、さっき大きなピースの塊を見つけたんだ。けれど、近くにモンスターがいてね。\n美しさに偏ったボクの肉体では、手も足も出ないのさ！\nどうだろう？　ボクの代わりに『古代壁画のピース』を回収してくれないかい？",
      "zh_TW": "哈哈！是我『王牌收藏家』大人的使者、瓦倫啦！\n收集到『古代壁畫的碎片』了嗎？\n其實啊～剛剛發現了一塊巨大的碎片。可是旁邊有魔物。\n對於我這美麗的身體來說，實在是手足無策！\n怎麼樣啊？可以代替我去回收『古代壁畫的碎片』嗎？"
    },
    {
      "id": "103",
      "ja_JP": "ハッハァー！　『キングコレクター』様の使い、ヴァーレンさ！\n大変だ！　『古代壁画のピース』集めに強力なライバル出現だ！\n『<value type=\"locationName\" id=\"fld002_E\"/>』のゴブリンたちが、ボクらと同じように壁画の修復をしているのさ！\nそのためにピースを強奪している連中もいる。\n放っておくわけにはいかない！　ヤツらを討伐して、奪われた『古代壁画のピース』を取り返してくれ！",
      "zh_TW": "哈哈！是我『王牌收藏家』大人的使者，瓦倫啦！\n糟糕了！出現也在收集『古代壁畫的碎片』的強力勁敵！\n『<value type=\"locationName\" id=\"fld002_E\"/>』的哥布林，也和我們一樣在修復壁畫！\n因為這樣也有一些傢伙和我們搶碎片。\n不能放任不管！討伐他們，搶回被奪走的『古代壁畫的碎片』！"
    },
    {
      "id": "16",
      "ja_JP": "やあ！　冒険は順調かい？\nボクの名はヴァーレン。相棒はカルネラ。\n蒐集家『キングコレクター』様の使いをしている者さ！\nお祭りと言えば、お菓子！　ステキなスイーツに興味はないかな？\nボクらは今、スイーツをたくさん集めているのさ。\n君にも手伝ってもらえると助かるんだけど、どうかな？\nきっと良いことがあると思うよ。ハッハァー！",
      "zh_TW": "嘿！冒險還順利嗎？\n我叫做瓦倫。同伴是卡涅拉。\n我們是蒐藏家『王牌收藏家』大人的使者！\n說到節慶就想到點心對吧！你對美妙的甜點有興趣嗎？\n我們現在正在收集大量的甜點。\n如果你也能來幫忙的話就太好了，如何啊？\n肯定有什麼好處的哦。哈哈！"
    },
    {
      "id": "17",
      "ja_JP": "ハッハァー！　『キングコレクター』様の使い、ヴァーレンさ！\n『フェイクスイーツ』集めは順調かな？\n実は、大食らいのモンスターが『フェイクスイーツ』を大量に食べてしまったと聞いてね。\nおいしそうだからしかたないけど、食べ尽くされては困るのさ！\nモンスターを討伐して、食べられた『フェイクスイーツ』も回収してもらえないかな？　よろしく頼むよ！",
      "zh_TW": "哈哈！是我『王牌收藏家』大人的使者，瓦倫啦！\n收集到『甜點模型』了嗎？\n其實呢～聽說有大食量的怪物吃了大量的『甜點模型』。\n很好吃是沒錯啦，但被他吃光可就傷腦筋了！\n可以請你去討伐怪物，回收被吃掉的『甜點模型』嗎？拜託了！"
    },
    {
      "id": "18",
      "ja_JP": "ハッハァー！　『キングコレクター』様の使い、ヴァーレンさ！\n行商人のみなさんが『フェイクスイーツ』を届けてくれると連絡があったんだけど、ちょっと困ったことになってね。\nどうやら途中でモンスターに奪われてしまったみたいなんだ。\n甘いもの好きなモンスターが、文字通り匂いを嗅ぎつけてね。\n『フェイクスイーツ』を取り戻したいし、モンスターを放っておくわけにもいかない！\n力を貸してもらえるかな？　頼むよ！",
      "zh_TW": "哈哈！是我『王牌收藏家』大人的使者，瓦倫啦！\n行商人那邊來連絡說會幫忙將『甜點模型』運送過來，但好像出了點狀況。\n好像在半路上被怪物打劫了。\n喜歡甜味的怪物可能問到氣味了吧。\n不只要取回『甜點模型』，也不能放任怪物不管！\n可以協助我們嗎？拜託了！"
    },
    {
      "id": "19",
      "ja_JP": "やあ！　アステルリーズの夏、満喫してるかい？\nボクの名はヴァーレン。相棒はカルネラ。\n蒐集家『キングコレクター』様の使いをしている者さ！\n突然だが、君は水着を持っているかい？\n持っていないなら、簡単な依頼を引き受けてみないか。\n報酬として、ナイスな水着をレンタルしよう！\n夏といえば水着！　君もこの波に乗り遅れるな！　ハッハァー！",
      "zh_TW": "嘿！冒險還順利嗎？\n我叫做瓦倫。同伴是卡涅拉。\n我們是蒐藏家『王牌收藏家』大人的使者！\n事出突然，你應該有帶著泳裝吧？\n如果沒有的話，要不要來做個簡單的委託呢。\n作為獎勵，借你一套非常棒的泳裝！\n想到夏天就想到泳裝！你也要趕上這波浪潮哦！哈哈！"
    },
    {
      "id": "20",
      "ja_JP": "ハッハァー！　『キングコレクター』様の使い、ヴァーレンさ！\n夏といえば何を想像する？　海？　太陽？　それとも肉体美？\nもちろんすべて正解だが、一つどうしても外せないものがある！\nそれはひと夏のアバンチュール！\n熱いまなざしが招く、燃え上がるほどの夏の幻想……。\nだが、せっかくの夏の視線を奪い去る奴らがいてね。\n冒険者さん、ボクらの夏を守ってもらえないかな？",
      "zh_TW": "哈哈！是我『王牌收藏家』大人的使者，瓦倫啦！\n說到夏天你會想像到什麼？沙灘？陽光？比基尼？\n都然每個答案都是正確的、但唯有一件事不能不提！\n那就是一整個夏天的大冒險！\n引來熱情的視線、燃燒般的夏日幻想……\n不過，有掃興的傢伙跑來奪走夏日的目光。\n冒險者，你願意守護大家的夏日嗎？"
    },
    {
      "id": "21",
      "ja_JP": "ハッハァー！　『キングコレクター』様の使い、ヴァーレンさ！\n貝殻ゴブリンを討伐してくれたおかげで、夏の視線をひとり占め！　のはずだったんだが……。\nまだだ……夏はまだこんなものではないはずさッ！\n水着の輝き！　向けられる熱い視線！　ああ、夏よ行かないで！\n貝殻ゴブリンに夏を奪われてはならない！\nさあ、もっともっと討伐しよう！　夏の視線は君に釘づけさ！",
      "zh_TW": "哈哈！是我『王牌收藏家』大人的使者，瓦倫啦！\n多虧有你幫忙討伐了貝殼哥布林，終於可以獨佔夏日的目光了！雖然我是很想這樣說的啦……\n不對……夏天不只是這樣才對！\n閃耀的泳裝！熱情的目光！哎呀，夏天別走！\n不可以被貝殼哥布林奪走夏天！\n來，再多討伐一些！讓夏日的目光聚焦在你身上！"
    },
    {
      "id": "22",
      "ja_JP": "やあ！　冒険は順調かい？\nボクの名はヴァーレン。相棒はカルネラ。\n蒐集家『キングコレクター』様の使いをしている者さ！\n主人は今、フワフワでやわらかいものを探していてね。\n『綿毛晶』がピンと来たみたいで、ひたすらかき集めているのさ。\nよかったら、君も手伝ってくれないかい？\nお礼はたくさん用意してあるからね！　ハッハァー！",
      "zh_TW": "嘿！冒險還順利嗎？\n我叫做瓦倫。同伴是卡涅拉。\n我們是蒐藏家『王牌收藏家』大人的使者！\n事出突然，你應該有帶著泳裝吧？\n如果沒有的話，要不要來做個簡單的委託呢。\n作為獎勵，借你一套非常棒的泳裝！\n想到夏天就想到泳裝！你也要趕上這波浪潮哦！哈哈！"
    },
    {
      "id": "23",
      "ja_JP": "ハッハァー！　『キングコレクター』様の使い、ヴァーレンさ！\n『綿毛晶』のフワフワっぷり、たまらないよね。\nそこでだ！　ボクも主人にならって『綿毛晶』を使ったオリジナルファッションに挑戦しようと思うのさ！\n『綿毛晶』集めのかたわら、手伝ってもらえないかな？",
      "zh_TW": "哈哈！是我『王牌收藏家』大人的使者，瓦倫啦！\n『棉毛晶』的柔軟觸感，很讓人上癮對吧。\n沒錯！我也想學習主人使用『棉毛晶』來挑戰原創的時尚流行！\n邊收集『棉毛晶』，順便幫我個忙吧？"
    },
    {
      "id": "24",
      "ja_JP": "ハッハァー！　『キングコレクター』様の使い、ヴァーレンさ！\n『キングコレクター』様の『綿毛晶』クッション作りも大詰め。\n極上のフワフワを包み込む、究極の布地が必要なんだ！\nここは冒険者さんの力を貸してもらうしかない。\n主人のフワフワな夢を叶えるために協力してくれ！　頼むよ、ハッハァー！",
      "zh_TW": "哈哈！是我『王牌收藏家』大人的使者，瓦倫啦！\n『王牌收藏家』大人的『棉毛晶』靠枕製作大業也進入最終階段。\n需要可以包入極致軟綿綿的，究極布料才行！\n需要冒險者的協助。\n請協助我們完成主人的軟綿綿夢想！拜託了，哈哈！"
    },
    {
      "id": "25",
      "ja_JP": "やあ！　冒険は順調かい？\nボクの名はヴァーレン。相棒はカルネラ。\n蒐集家『キングコレクター』様の使いをしている者さ！\nボクらは今、主人の命令で『白波の玉』を集めている。\n遠く古い異国の地から流れ着いたビーズでね、かつてはロマンあふれる絵巻物を形作っていたそうなんだ。\n冒険者さんも『白波の玉』を手に入れて、古代の異国のロマンに触れてみないかい？",
      "zh_TW": "嘿！冒險還順利嗎？\n我叫做瓦倫。同伴是卡涅拉。\n我們是蒐藏家『王牌收藏家』大人的使者！\n我們現在奉主人之命，正在收集『白波玉』。\n是一種從古代異國流傳而來的珠玉，過去曾用來製作充滿浪漫氣息的繪卷哦。\n冒險者也來收集『白波玉』，體驗看看古代異國的浪漫如何啊？"
    },
    {
      "id": "26",
      "ja_JP": "ハッハァー！　『キングコレクター』様の使い、ヴァーレンさ！\n『白波の玉』は続々と集まっているよ。\nこれも冒険者さんや皆の協力のおかげさ！\nところが、性懲りもなくゴブリンたちが『白波の玉』を奪い取っているみたいでね。\nヤツらが貯め込んだ分も集めてもらえないかな？",
      "zh_TW": "哈哈！是我『王牌收藏家』大人的使者，瓦倫啦！\n『白波玉』收集的很順利。\n這都是多虧了冒險者的福！\n話說回來，學不乖的哥布林好像在爭奪『白波玉』。\n可以幫我們搶回他們所囤積的份嗎？"
    },
    {
      "id": "27",
      "ja_JP": "ハッハァー！　『キングコレクター』様の使い、ヴァーレンさ！\n『白波の玉』と『天波の珠』集めはどうだい？\n気兼ねなく集めてほしいのに、またまたゴブリンの登場だ！\nどうにも『白波の玉』を諦めていないようでね。とうとう旅人や行商人に危害を加えそうになっているんだよ。\nこれは放置しておけない！\n冒険者さんの力を貸してくれ！",
      "zh_TW": "哈哈！是我『王牌收藏家』大人的使者，瓦倫啦！\n『白波玉』和『天波珠』收集的如何？\n雖然想請您專心收集，但是哥布林又現身了！\n看起來他們還沒放棄『白波玉』的樣子。而且好像開始對旅人及傷人出手了。\n不能夠放著不管！\n請冒險者助我們一臂之力！"
    },
    {
      "id": "138",
      "ja_JP": "やあ！　冒険は順調かい？\nボクの名はヴァーレン。相棒はカルネラ。\n蒐集家『キングコレクター』様の使いをしている者さ！\nボクらは今、主人の命令で『青薫の花弁』を集めている。\n幸せな花嫁と花婿を祝福し、見ているボクらもハッピーにしてくれるステキな贈り物さ！\nもちろん冒険者さんにも、豪華賞品と交換というハッピーが用意されているよ！\n『青薫の花弁』集めを手伝ってくれないかな！　ハッハァー！！",
      "zh_TW": "嘿！冒險還順利嗎？\n我叫做瓦倫。同伴是卡涅拉。\n我們是蒐藏家『王牌收藏家』大人的使者！\n我們現在奉主人之命，正在收集『青薰的花瓣』。\n除了祝賀新郎新娘幸福，光是看到的我們也會覺得開心的精美禮物！\n當然冒險者們也可以用它來交換豪華獎品來得到快樂!\n是否願意幫忙收集『青薰的花瓣』呢！哈哈！！"
    },
    {
      "id": "139",
      "ja_JP": "ハッハァー！　『キングコレクター』様の使い、ヴァーレンさ！\n『青薫の花弁』は順調に集まっているよ。\nところが、ゴブリンたちが花占いに使うことをあきらめていないようでね！\n今度はエルダーゴブリンが中心になって、『青薫の花弁』を持っていこうとしているのさ！\nおめでたい婚礼の季節！　祝福の気持ちを奪われるわけにはいかない！\nエルダーゴブリンの討伐に力を貸してくれないか！",
      "zh_TW": "哈哈！是我『王牌收藏家』大人的使者，瓦倫啦！\n『青薰的花瓣』收集的很順利。\n然而，哥布林們似乎還沒有放棄要拿花瓣來進行花的占卜。\n這一次是以哥布林長老為中心，想要奪走『青薰的花瓣』！\n在這個值得祝賀的婚禮季節，不能讓牠們將祝福的心情破壞！\n可以幫忙我們討伐哥布林長老嗎！"
    },
    {
      "id": "140",
      "ja_JP": "ハッハァー！　『キングコレクター』様の使い、ヴァーレンさ！\n『青薫の花弁』集めに、ピンチが訪れている！\n今度はムークたちが『青薫の花弁』を使って、何か大掛かりな儀式を企んでいるようなんだ！\nあちこちから『青薫の花弁』をかき集めて、一気に使ってしまうみたいでね。\nこれを見過ごすわけにはいかない！\n冒険者さん！　ムークの儀式を阻止して、『青薫の花弁』を守ってくれ！",
      "zh_TW": "哈哈！是我『王牌收藏家』大人的使者，瓦倫啦！\n『青薰的花瓣』的收集遇到了危機。\n這次是穆克們想要使用『青薰的花瓣』舉辦什麼大型的儀式！\n看來牠們想要到處地收集『青薰的花瓣』再一口氣地使用。\n我們不能讓這件事情不了了之！\n冒險者們！阻止穆克的儀式並守護『青薰的花瓣』吧！"
    },
    {
      "id": "28",
      "ja_JP": "やあ！　冒険は順調かい？\nボクの名はヴァーレン。相棒はカルネラ。\n蒐集家『キングコレクター』様の使いをしている者さ！\nボクらは今、主人の命令で『キングコレクターコイン』を集めている。\n『キングコレクター』様が勝手に作ったコインなんだけど、困ったことに盗難に遭ってしまってね！\n盗んだ連中を懲らしめて、『キングコレクターコイン』の回収に力を貸して欲しいのさ！",
      "zh_TW": "嘿！冒險還順利嗎？\r\n我叫做瓦倫。同伴是卡涅拉。\r\n我們是蒐藏家『王牌收藏家』大人的使者！\r\n我們現在奉主人之命，正在收集『王牌收藏家硬幣』。\r\n是『王牌收藏家』大人擅自打造的金幣，但傷腦筋的是遭到盜竊！\r\n希望你能夠教訓那些偷東西的傢伙，協助我們取回『王牌收藏家硬幣』！"
    },
    {
      "id": "29",
      "ja_JP": "ハッハァー！　『キングコレクター』様の使い、ヴァーレンさ！\n『キングコレクターコイン』を持っていそうな人を探していたら、有力情報が見つかったよ。\nなんと、ハイランドフォックスさ！\nコインが光るものだから、それにつられて拾い集めてしまったみたいだね。\n食べてしまったら大変だ！\n『キングコレクターコイン』の回収を手伝ってくれないか！",
      "zh_TW": "哈哈！是我『王牌收藏家』大人的使者，瓦倫啦！\n找了幾位可能擁有『王牌收藏家硬幣』的人物後，得到了可靠的情報。\n沒想到竟然是，高原狐！\n金幣閃閃發亮的，牠們好像因為受到吸引而撿走了。\n如果吃掉那可就糟了！\n可以協助我們回收『王牌收藏家硬幣』嗎！"
    },
    {
      "id": "30",
      "ja_JP": "ハッハァー！　『キングコレクター』様の使い、ヴァーレンさ！\n『キングコレクターコイン』が、またまた変な場所で見つかったよ！\nアステルリーズの闘技場さ！\nなんと、闘技場の賞金に『キングコレクターコイン』が混ざっているみたいなんだ！\nこれを渡されたら、普通の人は怒ると思うね！\n闘技場をクリアして、こっそり回収してくれないかな？",
      "zh_TW": "哈哈！是我『王牌收藏家』大人的使者，瓦倫啦！\n『王牌收藏家硬幣』又在奇怪的地方被找到了！\n就在亞斯特里茲的競技場！\n沒想到，『王牌收藏家硬幣』混入競技場的賞金裡了！\n如果一般人收到錯的金幣，肯定會抓狂的！\n可以請你通過競技場，偷偷把它們回收嗎？"
    },
    {
      "id": "65",
      "ja_JP": "やあ！　冒険は順調かい？\nボクの名はヴァーレン。相棒はカルネラ。\n蒐集家『キングコレクター』様の使いをしている者さ！\nボクらは今、主人の命令で『華麗に香る種』を集めている。\n素晴らしく刺激的な香りを放つ種でね。かつては伝統料理に使われたけど、あまりに刺激的だから今ではなかなか見かけないのさ！\n冒険者さんも刺激に満ちた種集めを体験してみないかい？\n『華麗に香る種』を集めて、豪華賞品と交換しよう！",
      "zh_TW": "嘿！冒險還順利嗎？\n我叫做瓦倫。同伴是卡涅拉。\n我們是蒐藏家『王牌收藏家』大人的使者！\n我們現在奉主人之命，正在收集『華麗香氣種子』。\n是一種散發著美妙且刺鼻香氣的種子。過去曾被使用在傳統料理上，但因為太過刺鼻了現今已經很少見到!\n冒險者要不要也來體驗看看充滿刺激的種子收集啊?\n收集『華麗香氣種子』來交換獎品吧!"
    },
    {
      "id": "66",
      "ja_JP": "ハッハァー！　『キングコレクター』様の使い、ヴァーレンさ！\n『キングコレクター』様が、砂漠の伝統料理のオリジナルを食べてみたいと言うものでね。\n『華麗に香る種』の刺激的な香りをさらに引き立てるべく、古い文献を漁っていろいろ試しているのさ！\nそうなると『華麗に香る種』がもっと必要になるんだけど、ゴブリンたちが香りを気に入ってしまったみたいだ。\nこのままだと、『華麗に香る種』を集める時に邪魔をされてしまうかもしれない。\nゴブリン討伐に力を貸してくれると助かるよ！",
      "zh_TW": "哈哈！是我『王牌收藏家』大人的使者，瓦倫啦！\n『王牌收藏家』大人說，想要吃吃看沙漠的傳統傳創料理。\n為了更加利用『華麗香氣種子』那刺激的香味，正在閱讀古文獻嘗試各種做法！\n也因此需要更多的『華麗香氣種子』，但哥布林好像也被這種氣味所吸引了。\n這樣的話，在收集『華麗香氣種子』時有受告干擾的可能。\n請務必協助我們討伐哥布林！"
    },
    {
      "id": "67",
      "ja_JP": "ハッハァー！！　『キングコレクター』様の使い、華麗なる美しき魅惑のボディ！！　ヴァーレンさ！！\n『華麗に香る種』は集まっているかな！！\nモンスターも魅了してやまない刺激的な香り！！　そして味！！\n今度はムークが虜にされたみたいだよ！！\n『華麗に香る種』を取り返さなければ！！",
      "zh_TW": "哈哈！是我『王牌收藏家』大人的使者，瓦倫啦！\n『華麗香氣種子』收集的如何啊！！\n連怪物都被魅惑的刺激香味！！還有味道！！\n這次換穆克成為它的俘虜了！！\n得取回『華麗香氣種子』才行！！"
    },
    {
      "id": "113",
      "ja_JP": "やあ！　冒険は順調かい？\nボクの名はヴァーレン。相棒はカルネラ。\n蒐集家『キングコレクター』様の使いをしている者さ！\nボクらは今、主人の命令で『こぼれ星の砂』を集めている。\nこの時期に空から降ってくる、幻想的な欠片のことさ！\n星の形をした砂に願いをかけるなんて、ロマンチックだと思わないかい？\n『こぼれ星の砂』を集めるために手を貸してほしい！\nよろしく頼むよ、ハッハァー！",
      "zh_TW": "嘿！冒險還順利嗎？\n我叫做瓦倫。同伴是卡涅拉。\n我們是蒐藏家『王牌收藏家』大人的使者！\n我們現在奉主人之命，正在收集『滿天星之砂』。\n是一種在這個季節會從天而降，充滿幻想氣息的碎片！\n向星星狀的砂子許願，不覺得很浪漫嗎？\n請協助我們收集『滿天星之砂』！\n拜託你啦，哈哈！"
    },
    {
      "id": "114",
      "ja_JP": "ハッハァー！　『キングコレクター』様の使い、ヴァーレンさ！\n『こぼれ星の砂』は集まっているかな？\n子供たちも願いごとをしながら集めているんだけど、悪い話を聞いたのさ！\nせっかく集めた『こぼれ星の砂』を山賊に奪われてしまったということでね。\nこれは見過ごすわけにはいかないよ！\n不届きな連中から『こぼれ星の砂』を取り戻してほしいんだ！",
      "zh_TW": "哈哈！是我『王牌收藏家』大人的使者，瓦倫啦！\n收集到『滿天星之砂』了嗎？\n聽說小朋友們也為了許願而收集，但也有不好的消息！\n好不容易收集到的『滿天星之砂』被怪物給搶走了。\n這可不能放任不管！\n討伐怪物並取回『滿天星之砂』吧！"
    },
    {
      "id": "115",
      "ja_JP": "ハッハァー！　『キングコレクター』様の使い、ヴァーレンさ！\n『こぼれ星の砂』集めは順調かい？\n皆も楽しんでいるんだけど、ちょっと困った噂が流れているんだ。\n「苦労して集めた『こぼれ星の砂』のほうが、願いごとが叶いやすい」っていうのさ。\nこれを真に受けた若者たちが『鎮まりの山麓』へ行こうとしているみたいでね。\nモンスターを討伐して、あそこが危険な場所だということを教えてあげてくれないかな？",
      "zh_TW": "哈哈！是我『王牌收藏家』大人的使者，瓦倫啦！\n收集『滿天星之砂』還順利嗎？\n雖然大家都樂在其中，但聽說了令人困擾的消息。\n流傳「越是辛苦取得的『滿天星之砂』，更能達成願望」。\n信以為真的人似乎想前往『平靜的山麓』。\n協助討伐怪物，並告知大家那裡是危險的地方好嗎？"
    },
    {
      "id": "77",
      "ja_JP": "やあ！　冒険は順調かい？\nボクの名はヴァーレン。相棒はカルネラ。\n蒐集家『キングコレクター』様の使いをしている者さ！\nボクらは今、主人の命令で『聖夜のメリーレッド』を集めている。\n若木を鮮やかに飾って、聖なる夜に皆の願いをかけるのさ！\n冒険者さんにも、豪華賞品と交換というステキなプレゼントが待っているよ！\n『聖夜のメリーレッド』を集めてくれないかな！　ハッハァー！！",
      "zh_TW": "嘿！冒險還順利嗎？\n我叫做瓦倫。同伴是卡涅拉。\n我們是蒐藏家『王牌收藏家』大人的使者！\n我們現在奉主人之命，正在收集『聖誕彩球』。\n把樹木裝飾起來，在聖夜許下大家的心願！\n對冒險者來說，也有著交換豪華獎品這樣的美妙禮物哦！\n可以幫忙收集『聖誕彩球』嗎！哈哈！！"
    },
    {
      "id": "78",
      "ja_JP": "ハッハァー！　『キングコレクター』様の使い、ヴァーレンさ！\n『聖夜のメリーレッド』集めは順調かな？\nボクらは飾り付けをするための若木を用意したよ。\nところが、『雪かぶりのボア』があちこちに現れてね。大事な若木の芽を食べてしまっているんだ！\nこれから子供たちと一緒に、すくすく育っていくというのに！\n冒険者さん、『雪かぶりのボア』を討伐してくれないかい？\nステキなお祭りを守るためにもよろしく頼むよ！　ハッハァー！",
      "zh_TW": "哈哈！是我『王牌收藏家』大人的使者，瓦倫啦！\n收集『聖誕彩球』還順利嗎？\n我已經準備好要用來裝飾的樹嘍。\n話說回來，各地出現了『披雪的波亞』。牠們要把重要的樹木幼芽吃光了！\n這些樹是要和小朋友們，慢慢栽培的！\n冒險者，可以協助討伐『披雪的波亞』嗎？\n為了守護美妙的慶典可萬事拜託了！哈哈！"
    },
    {
      "id": "79",
      "ja_JP": "ハッハァー！　『キングコレクター』様の使い、ヴァーレンさ！\n『聖夜のメリーレッド』はどんどん集まっているよ！\n冒険者さんのおかげで聖なる夜も大盛り上がりさ！\nところが、『雪かぶりのボア』までお祭りの雰囲気で盛り上がってしまったのかな？\nなんだか数が増えてきている気がするのさ！\n『聖夜のメリーレッド』を飲み込んだ奴らもいるみたいだし、冒険者さんの手で追い払ってくれ！",
      "zh_TW": "哈哈！是我『王牌收藏家』大人的使者，瓦倫啦！\n『聖誕彩球』收集的很順利。\n這都是多虧了冒險者的福！\n話說回來，是不是連『披雪的波亞』都因為慶典的氣氛而興奮起來了啊？\n總感覺數量還增加了！\n甚至還有把『聖誕彩球』吞下去的傢伙，冒險者請快點想想辦法！"
    },
    {
      "id": "89",
      "ja_JP": "やあ！　冒険は順調かい？\nボクの名はヴァーレン。相棒はカルネラ。\n蒐集家『キングコレクター』様の使いをしている者さ！\nボクらは今、主人の命令で『春粧ひ花』を集めている。\n遠い異国の地で、新たな年を祝うための縁起物さ！\nたくさん集めて、皆でおめでたい気分を分かち合おう！\nお礼に豪華賞品も用意しているからよろしくね！　ハッハァー！",
      "zh_TW": "嘿！冒險還順利嗎？\n我叫做瓦倫。同伴是卡涅拉。\n我們是蒐藏家『王牌收藏家』大人的使者！\n我們現在奉主人之命，正在收集『春之花柔』。\n在遙遠的異地，用來慶祝新年的吉利物品！\n大量收集，與大家來分享值得慶祝的心情吧！\n作為謝禮也會準備豪華的獎品哦！哈哈！"
    },
    {
      "id": "90",
      "ja_JP": "ハッハァー！　『キングコレクター』様の使い、ヴァーレンさ！\n『春粧ひ花』を集めてくれてありがとう！\n順調に集まっていたんだけど、予想外のライバルが登場だ！\nスカイフィッシュが『春粧ひ花』の美しさに惹かれて、片っ端から食べてしまっているようなのさ！\n『春粧ひ花』集めを邪魔されてもいけない！\nスカイフィッシュ討伐に力を貸してくれないかな！",
      "zh_TW": "哈哈！是我『王牌收藏家』大人的使者，瓦倫啦！\n感謝協助收集『春之花柔』！\n雖然收集作業很順利，但卻出現了意料之外的勁敵！\n飛翼魚被『春之花柔』的美麗給吸引，竟然吃起來了！\n『春之花柔』的收集不容任何干擾！\n請協助我們討伐飛翼魚！"
    },
    {
      "id": "91",
      "ja_JP": "ハッハァー！　『キングコレクター』様の使い、ヴァーレンさ！\n『春粧ひ花』が集まって美しく、おめでたいね！\nそんなおめでたさがモンスターの心も惹きつけるのかな？\nホーンゴートが『春粧ひ花』で寝床を飾っているのさ！\n趣があって美しいと言いたいけれど、人のいる場所から『春粧ひ花』を奪っているようでね。\nこれはいけない！　美しくない！\nホーンゴート討伐に力を貸してくれ！　ハッハァー！",
      "zh_TW": "哈哈！是我『王牌收藏家』大人的使者，瓦倫啦！\n『春之花柔』又美麗，又很有節慶氣氛吧！\n是這種值得慶祝的部分吸引到怪物嗎？\n角羊竟然用『春之花柔』來裝飾自己的巢穴！\n雖然很想說真有品味啦，但牠們開始在有人的地方搶奪『春之花柔』了。\n這可不行！一點都不美！\n請務必協助我們討伐角羊！哈哈！"
    },
    {
      "id": "125",
      "ja_JP": "やあ！　冒険は順調かい？\nボクの名はヴァーレン。相棒はカルネラ。\n蒐集家『キングコレクター』様の使いをしている者さ！\nボクらは今、主人の命令で『妖精レンゲの蜜』を集めている。\nとっても甘～くてキラキラしている花の蜜でね。\nこれを使ったお菓子を街の皆さんに振る舞いたいんだ！\n冒険者さんも手を貸してくれないかな？\n『妖精レンゲの蜜』を集めてくれたら、豪華賞品と交換しよう！",
      "zh_TW": "嘿！冒險還順利嗎？\n我叫做瓦倫。同伴是卡涅拉。\n我們是蒐藏家『王牌收藏家』大人的使者！\n我們現在奉主人之命，正在收集『妖精花蜜』。\n它是非常甜美又會閃閃發光的花蜜喔！\n我們想讓城裡的大家嘗嘗使用它所作成的甜點!\n冒險者們是否願意幫忙呢？\n只要幫忙我們收集『妖精花蜜』，就能交換豪華禮品喔！"
    },
    {
      "id": "126",
      "ja_JP": "ハッハァー！　『キングコレクター』様の使い、ヴァーレンさ！\n『妖精レンゲの蜜』を使ったお菓子は、おかげさまで好評だよ！\nところが、『キングコレクター』様が「オンリーワンになるような、もうひと工夫したい！」ってわがままを言い出してね。\nそこで遊び心のある色合いを加えてみようと思うのさ！\n素材集めを手伝ってもらえないかな？",
      "zh_TW": "哈哈！是我『王牌收藏家』大人的使者，瓦倫啦！\n托您的福『妖精花蜜』所作成的甜點大受好評！\n然而，『王牌收藏家』又任性地說出希望「我想多加點功夫讓它變得獨一無二！」的話。\n它很希望能夠再添加一些玩心在裡面！\n所以可以麻煩您幫忙收集材料嗎！"
    },
    {
      "id": "127",
      "ja_JP": "ハッハァー！　『キングコレクター』様の使い、ヴァーレンさ！\n『妖精レンゲの蜜』集めをありがとう！\nお菓子作りも盛り上がってきて、街の皆さんも一緒に作ろうということになったのさ！\nところが、材料を提供してくれる農園がモンスターに荒らされて困っているらしい。\nお世話になりっ放しというワケにはいかない！\n農園の皆さんを助けるために冒険者さんの力を貸してほしいんだ！",
      "zh_TW": "哈哈！是我『王牌收藏家』大人的使者，瓦倫啦！\n謝謝您幫忙收集『妖精花蜜』！\n甜點製作活動越來越熱鬧，城裡的人們也決定要一起製作了。\n不過提供材料的農園似乎因為受到怪物的侵襲而感到困擾，\n收到了他們幫忙的我們可不能置之不理！\n為了要幫忙農園的大家希望冒險者可以祝我們一臂之力！"
    },
    {
      "id": "104",
      "ja_JP": "アステルリーズ　ヴァーレンと話をしよう",
      "zh_TW": "亞斯特里茲　與瓦倫交談"
    },
    {
      "id": "105",
      "ja_JP": "アステルリーズ　ヴァーレンと話をしよう",
      "zh_TW": "亞斯特里茲　與瓦倫交談"
    },
    {
      "id": "106",
      "ja_JP": "アステルリーズ　ヴァーレンと話をしよう",
      "zh_TW": "亞斯特里茲　與瓦倫交談"
    },
    {
      "id": "31",
      "ja_JP": "アステルリーズ　ヴァーレンと話をしよう",
      "zh_TW": "亞斯特里茲　與瓦倫交談"
    },
    {
      "id": "32",
      "ja_JP": "アステルリーズ　ヴァーレンと話をしよう",
      "zh_TW": "亞斯特里茲　與瓦倫交談"
    },
    {
      "id": "33",
      "ja_JP": "アステルリーズ　ヴァーレンと話をしよう",
      "zh_TW": "亞斯特里茲　與瓦倫交談"
    },
    {
      "id": "34",
      "ja_JP": "アステルリーズ　ヴァーレンと話をしよう",
      "zh_TW": "亞斯特里茲　與瓦倫交談"
    },
    {
      "id": "35",
      "ja_JP": "アステルリーズ　ヴァーレンと話をしよう",
      "zh_TW": "亞斯特里茲　與瓦倫交談"
    },
    {
      "id": "36",
      "ja_JP": "アステルリーズ　ヴァーレンと話をしよう",
      "zh_TW": "亞斯特里茲　與瓦倫交談"
    },
    {
      "id": "37",
      "ja_JP": "アステルリーズ　ヴァーレンと話をしよう",
      "zh_TW": "亞斯特里茲　與瓦倫交談"
    },
    {
      "id": "38",
      "ja_JP": "アステルリーズ　ヴァーレンと話をしよう",
      "zh_TW": "亞斯特里茲　與瓦倫交談"
    },
    {
      "id": "39",
      "ja_JP": "アステルリーズ　ヴァーレンと話をしよう",
      "zh_TW": "亞斯特里茲　與瓦倫交談"
    },
    {
      "id": "40",
      "ja_JP": "アステルリーズ　ヴァーレンと話をしよう",
      "zh_TW": "亞斯特里茲　與瓦倫交談"
    },
    {
      "id": "41",
      "ja_JP": "アステルリーズ　ヴァーレンと話をしよう",
      "zh_TW": "亞斯特里茲　與瓦倫交談"
    },
    {
      "id": "42",
      "ja_JP": "アステルリーズ　ヴァーレンと話をしよう",
      "zh_TW": "亞斯特里茲　與瓦倫交談"
    },
    {
      "id": "141",
      "ja_JP": "アステルリーズ　ヴァーレンと話をしよう",
      "zh_TW": "亞斯特里茲　與瓦倫交談"
    },
    {
      "id": "142",
      "ja_JP": "アステルリーズ　ヴァーレンと話をしよう",
      "zh_TW": "亞斯特里茲　與瓦倫交談"
    },
    {
      "id": "143",
      "ja_JP": "アステルリーズ　ヴァーレンと話をしよう",
      "zh_TW": "亞斯特里茲　與瓦倫交談"
    },
    {
      "id": "43",
      "ja_JP": "アステルリーズ　ヴァーレンと話をしよう",
      "zh_TW": "亞斯特里茲　與瓦倫交談"
    },
    {
      "id": "44",
      "ja_JP": "アステルリーズ　ヴァーレンと話をしよう",
      "zh_TW": "亞斯特里茲　與瓦倫交談"
    },
    {
      "id": "45",
      "ja_JP": "アステルリーズ　ヴァーレンと話をしよう",
      "zh_TW": "亞斯特里茲　與瓦倫交談"
    },
    {
      "id": "68",
      "ja_JP": "アステルリーズ　ヴァーレンと話をしよう",
      "zh_TW": "亞斯特里茲　與瓦倫交談"
    },
    {
      "id": "69",
      "ja_JP": "アステルリーズ　ヴァーレンと話をしよう",
      "zh_TW": "亞斯特里茲　與瓦倫交談"
    },
    {
      "id": "70",
      "ja_JP": "アステルリーズ　ヴァーレンと話をしよう",
      "zh_TW": "亞斯特里茲　與瓦倫交談"
    },
    {
      "id": "116",
      "ja_JP": "アステルリーズ　ヴァーレンと話をしよう",
      "zh_TW": "亞斯特里茲　與瓦倫交談"
    },
    {
      "id": "117",
      "ja_JP": "アステルリーズ　ヴァーレンと話をしよう",
      "zh_TW": "亞斯特里茲　與瓦倫交談"
    },
    {
      "id": "118",
      "ja_JP": "アステルリーズ　ヴァーレンと話をしよう",
      "zh_TW": "亞斯特里茲　與瓦倫交談"
    },
    {
      "id": "80",
      "ja_JP": "アステルリーズ　ヴァーレンと話をしよう",
      "zh_TW": "亞斯特里茲　與瓦倫交談"
    },
    {
      "id": "81",
      "ja_JP": "アステルリーズ　ヴァーレンと話をしよう",
      "zh_TW": "亞斯特里茲　與瓦倫交談"
    },
    {
      "id": "82",
      "ja_JP": "アステルリーズ　ヴァーレンと話をしよう",
      "zh_TW": "亞斯特里茲　與瓦倫交談"
    },
    {
      "id": "92",
      "ja_JP": "アステルリーズ　ヴァーレンと話をしよう",
      "zh_TW": "亞斯特里茲　與瓦倫交談"
    },
    {
      "id": "93",
      "ja_JP": "アステルリーズ　ヴァーレンと話をしよう",
      "zh_TW": "亞斯特里茲　與瓦倫交談"
    },
    {
      "id": "94",
      "ja_JP": "アステルリーズ　ヴァーレンと話をしよう",
      "zh_TW": "亞斯特里茲　與瓦倫交談"
    },
    {
      "id": "128",
      "ja_JP": "アステルリーズ　ヴァーレンと話をしよう",
      "zh_TW": "亞斯特里茲　與瓦倫交談"
    },
    {
      "id": "129",
      "ja_JP": "アステルリーズ　ヴァーレンと話をしよう",
      "zh_TW": "亞斯特里茲　與瓦倫交談"
    },
    {
      "id": "130",
      "ja_JP": "アステルリーズ　ヴァーレンと話をしよう",
      "zh_TW": "亞斯特里茲　與瓦倫交談"
    },
    {
      "id": "46",
      "ja_JP": "テンデル糸",
      "zh_TW": "歌曲系"
    },
    {
      "id": "131",
      "ja_JP": "転色タンポポ",
      "zh_TW": "變色蒲公英"
    },
    {
      "id": "107",
      "ja_JP": "ミンスター丘陵　{enemyId}を倒そう{progress}",
      "zh_TW": "明斯特丘陵　打倒{enemyId}{progress}"
    },
    {
      "id": "108",
      "ja_JP": "アンドラ盆地　{enemyId}を倒そう{progress}",
      "zh_TW": "安道爾盆地　打倒{enemyId}{progress}"
    },
    {
      "id": "109",
      "ja_JP": "鎮まりの山麓　{enemyId}を倒そう{progress}",
      "zh_TW": "平靜的山麓　打倒{enemyId}{progress}"
    },
    {
      "id": "47",
      "ja_JP": "ミンスター丘陵　{enemyId}を倒そう{progress}",
      "zh_TW": "明斯特丘陵　打倒{enemyId}{progress}"
    },
    {
      "id": "48",
      "ja_JP": "アンドラ盆地　{enemyId}を倒そう{progress}",
      "zh_TW": "安道爾盆地　打倒{enemyId}{progress}"
    },
    {
      "id": "49",
      "ja_JP": "鎮まりの山麓　{enemyId}を倒そう{progress}",
      "zh_TW": "平靜的山麓　打倒{enemyId}{progress}"
    },
    {
      "id": "50",
      "ja_JP": "ミンスター丘陵　{enemyId}を倒そう{progress}",
      "zh_TW": "明斯特丘陵　打倒{enemyId}{progress}"
    },
    {
      "id": "51",
      "ja_JP": "アンドラ盆地　{enemyId}を倒そう{progress}",
      "zh_TW": "安道爾盆地　打倒{enemyId}{progress}"
    },
    {
      "id": "52",
      "ja_JP": "鎮まりの山麓　{enemyId}を倒そう{progress}",
      "zh_TW": "平靜的山麓　打倒{enemyId}{progress}"
    },
    {
      "id": "53",
      "ja_JP": "巨竜の爪痕・自由　{enemyId}を倒そう{progress}",
      "zh_TW": "巨龍的爪痕・自由　打倒{enemyId}{progress}"
    },
    {
      "id": "54",
      "ja_JP": "ミンスター丘陵　テンデル糸を集めよう{progress}",
      "zh_TW": "明斯特丘陵　收集歌曲系物品{progress}"
    },
    {
      "id": "55",
      "ja_JP": "虚空の浮島を3回クリアしよう{progress}",
      "zh_TW": "完成3次虛空的浮島・土龍襲來{progress}"
    },
    {
      "id": "56",
      "ja_JP": "ミンスター丘陵　{enemyId}を倒そう{progress}",
      "zh_TW": "明斯特丘陵　打倒{enemyId}{progress}"
    },
    {
      "id": "57",
      "ja_JP": "アンドラ盆地　{enemyId}を倒そう{progress}",
      "zh_TW": "安道爾盆地　打倒{enemyId}{progress}"
    },
    {
      "id": "58",
      "ja_JP": "鎮まりの山麓　{enemyId}を倒そう{progress}",
      "zh_TW": "平靜的山麓　打倒{enemyId}{progress}"
    },
    {
      "id": "144",
      "ja_JP": "ミンスター丘陵　{enemyId}を倒そう{progress}",
      "zh_TW": "明斯特丘陵　打倒{enemyId}{progress}"
    },
    {
      "id": "145",
      "ja_JP": "アンドラ盆地　{enemyId}を倒そう{progress}",
      "zh_TW": "安道爾盆地　打倒{enemyId}{progress}"
    },
    {
      "id": "146",
      "ja_JP": "鎮まりの山麓　{enemyId}を倒そう{progress}",
      "zh_TW": "平靜的山麓　打倒{enemyId}{progress}"
    },
    {
      "id": "59",
      "ja_JP": "アンドラ盆地　{enemyId}を倒そう{progress}",
      "zh_TW": "安道爾盆地　打倒{enemyId}{progress}"
    },
    {
      "id": "60",
      "ja_JP": "神の見守る丘　{enemyId}を倒そう{progress}",
      "zh_TW": "神明守護的山丘　打倒{enemyId}{progress}"
    },
    {
      "id": "61",
      "ja_JP": "ラッシュバトル・初段を攻略しよう",
      "zh_TW": "攻略競技場・1階"
    },
    {
      "id": "71",
      "ja_JP": "海鳴りの草原　{enemyId}を倒そう{progress}",
      "zh_TW": "海鳴之草原　打倒{enemyId}{progress}"
    },
    {
      "id": "72",
      "ja_JP": "ミンスター丘陵　{enemyId}を倒そう{progress}",
      "zh_TW": "明斯特丘陵　打倒{enemyId}{progress}"
    },
    {
      "id": "73",
      "ja_JP": "リッツェ交易街道　{enemyId}を倒そう{progress}",
      "zh_TW": "里茲貿易街道　打倒{enemyId}{progress}"
    },
    {
      "id": "119",
      "ja_JP": "ミンスター丘陵　{enemyId}を倒そう{progress}",
      "zh_TW": "明斯特丘陵　打倒{enemyId}{progress}"
    },
    {
      "id": "120",
      "ja_JP": "アンドラ盆地　{enemyId}を倒そう{progress}",
      "zh_TW": "安道爾盆地　打倒{enemyId}{progress}"
    },
    {
      "id": "121",
      "ja_JP": "鎮まりの山麓　{enemyId}を倒そう{progress}",
      "zh_TW": "平靜的山麓　打倒{enemyId}{progress}"
    },
    {
      "id": "83",
      "ja_JP": "ミンスター丘陵　{enemyId}を倒そう{progress}",
      "zh_TW": "明斯特丘陵　打倒{enemyId}{progress}"
    },
    {
      "id": "84",
      "ja_JP": "アンドラ盆地　{enemyId}を倒そう{progress}",
      "zh_TW": "安道爾盆地　打倒{enemyId}{progress}"
    },
    {
      "id": "85",
      "ja_JP": "鎮まりの山麓　{enemyId}を倒そう{progress}",
      "zh_TW": "平靜的山麓　打倒{enemyId}{progress}"
    },
    {
      "id": "95",
      "ja_JP": "海鳴りの平原　{enemyId}を倒そう{progress}",
      "zh_TW": "海鳴之草原　打倒{enemyId}{progress}"
    },
    {
      "id": "96",
      "ja_JP": "ミンスター丘陵　{enemyId}を倒そう{progress}",
      "zh_TW": "明斯特丘陵　打倒{enemyId}{progress}"
    },
    {
      "id": "97",
      "ja_JP": "神の見守る丘　{enemyId}を倒そう{progress}",
      "zh_TW": "神明守護的山丘　打倒{enemyId}{progress}"
    },
    {
      "id": "132",
      "ja_JP": "ミンスター丘陵　{enemyId}を倒そう{progress}",
      "zh_TW": "明斯特丘陵　打倒{enemyId}{progress}"
    },
    {
      "id": "133",
      "ja_JP": "ミンスター丘陵　転色タンポポを集めよう{progress}",
      "zh_TW": "明斯特丘陵　收集變色蒲公英{progress}"
    },
    {
      "id": "134",
      "ja_JP": "神の見守る丘　{enemyId}を倒そう{progress}",
      "zh_TW": "神明守護的山丘　打倒{enemyId}{progress}"
    }
  ]
}